README.rst
setup.py
tarnish.py
tarnish.egg-info/PKG-INFO
tarnish.egg-info/SOURCES.txt
tarnish.egg-info/dependency_links.txt
tarnish.egg-info/entry_points.txt
tarnish.egg-info/top_level.txt