Metadata-Version: 1.1
Name: tarnish
Version: 0.1
Summary: Can't handle my tarn
Home-page: https://github.com/icio/tarnish
Author: Paul Scott, Duedil Limited
Author-email: paul@duedil.com
License: MIT
Download-URL: https://github.com/icio/tarnish/tarball/0.1
Keywords: tarnfeld,tarnfeid,tarn,can't handle my
Platform: UNKNOWN
